Broken quartus projects/RGB_TO_HSV/RGB_TO_HSV_COMB.sv
module RGB_TO_HSV_COMB(
	input logic	[23:0] rgb,
	output logic [23:0] hsv
	
);

////////////////////////////////////////////////////////////////////////
parameter POINT = 24;

///////////////////////////////////////////////////////////////////////

//Division lookup table 
logic signed [POINT+2:0] div_lookup[255:0];
logic[7:0] hue, saturation, value, cmin, cmax, delta;
logic[31:0] saturation_fixed;
logic signed[64:0] hue_debug, hue_step1_debug;
logic [7:0] hue_cond_debug;

logic[8:0] red, green, blue;
logic signed[8:0] gmb, bmr, rmg;
logic[POINT+10:0] hue_step1;

//Debug logic
logic[POINT+2 + 8:0] saturation_intermediate;

//Lookup table initialization

initial begin
	div_lookup[0] = 0;
	for (int i = 1; i < 256; i = i+1)  begin
		div_lookup[i] = (32'h1<<POINT)/i;
	end
end

always @(*) begin
	//RGB splitting
	red = {1'b0, rgb[23:16]};
	green = {1'b0, rgb[15:8]};
	blue = {1'b0, rgb[7:0]};
	
	//Differences
	gmb = green - blue;
	bmr = blue - red;
	rmg = red - green;
	
	//Cmax calculation
	if (red >= blue & red >= green) begin 
		cmax = red;
	end else if (green >= red & green >= blue) begin
		cmax = green;
	end else begin
		cmax = blue;
	end
	
	//Cmin calculation
	if (red <= blue & red <= green) cmin = red;
	else if (green <= red & green <= blue) cmin = green;
	else cmin = blue;
	
	//Delta
	delta = cmax-cmin;
	
	//Hue calculation
	if (red >= blue & red >= green) begin 
		if (green >= blue) begin
			hue_step1 = ((gmb)*div_lookup[delta]);
		end else begin
			hue_step1 = ((gmb)*div_lookup[delta] + (6 << POINT));
		end
			
	end else if (green >= red & green >= blue) begin
		hue_step1 = (((bmr)*div_lookup[delta]) + (2 << POINT));
		
	end else begin
		hue_step1 = (((rmg)*div_lookup[delta]) + (4 << POINT));
	end
	//Hue scaling
	hue = (30* hue_step1)>>POINT;

	//Saturation calulation
	saturation_intermediate = delta * div_lookup[cmax];
	saturation = (255 * saturation_intermediate) >>> POINT;
	
	value = cmax;
		
	hsv = {hue, saturation, value}; 
		
end

endmodule

DE10_CAM_MEMORY/ip/RGB_TO_HSV/STREAM_REG.sv
module STREAM_REG(ready_out, valid_out, data_out, ready_in, valid_in, data_in, clk, rst_n);

	// Input Port(s)
	input clk, rst_n;
	input ready_in, valid_in;
	input [DATA_WIDTH-1:0] data_in;
	
	// Output Port(s)
	output ready_out, valid_out;
	output reg [DATA_WIDTH-1:0] data_out;

	// Parameter Declaration(s)
	parameter DATA_WIDTH = 26;
	
	reg data_valid, ready_in_d;

	always@(posedge clk) begin
		if (~rst_n) begin
			data_out <= 1'b0;
			data_valid <= 0;
			ready_in_d <= 0;
			end
		else begin
			ready_in_d <= ready_in;
			if (valid_in & (~data_valid | ready_in_d)) begin
				data_out <= data_in;
				data_valid <= 1;
				end
			else if (ready_in_d) begin
				data_valid <= 0;
				end
			end
	end
	
	assign ready_out = (~data_valid & ~valid_in) | ready_in;
	assign valid_out = ready_in_d & data_valid;
	//assign advance = valid_in & (~data_valid | ready_in_d);


endmodule

DE10_CAM_FRESH/ip/COM_COUNTER/COM_COUNTER.sv
module RGB_TO_HSV(
	//global clock & reset
	input logic	clk,
	input logic reset_n,
	
	// stream sink
	input logic	[23:0] sink_data,
	input logic sink_valid,
	output logic sink_ready,
	input logic sink_sop,
	input logic sink_eop,
	
	// streaming source
	output logic [23:0] source_data,
	output logic source_valid,
	input logic source_ready,
	output logic source_sop,
	output logic source_eop
	
);

//Intermediate declarations
logic[23:0] rgb, hsv, hsv_comb;
logic sop, eop, ready, valid;


always @(*) begin
	if (sop) begin
		hsv = rgb;
	end else begin
		hsv = hsv_comb;
	end
	
end


//Streaming registers to buffer video signal
STREAM_REG #(.DATA_WIDTH(26)) in_reg (
	//Global clocks
	.clk(clk),
	.rst_n(reset_n),
	
	//Sink inputs
	.ready_out(sink_ready),
	.valid_in(sink_valid),
	.data_in({sink_data,sink_sop,sink_eop}),
	
	//Internal ports
	.ready_in(ready),
	.valid_out(valid),
	.data_out({rgb,sop,eop})
);

STREAM_REG #(.DATA_WIDTH(26)) out_reg (
	//Global clocks
	.clk(clk),
	.rst_n(reset_n),
	
	//Internal ports
	.ready_out(ready),
	.valid_in(valid),
	.data_in({hsv, sop, eop}),
	
	//source ports
	
	.ready_in(source_ready),
	.valid_out(source_valid),
	.data_out({source_data,source_sop,source_eop})
);

RGB_TO_HSV_COMB rgbtohsv (.rgb(rgb), .hsv(hsv_comb));
	


endmodule

DE10_CAM_FILTER/ip/RGB_TO_HSV/RGB_TO_HSV_TB.sv
module RGB_TO_HSV_TB ();
    logic clk, reset_n;
	logic [23:0] source_data, sink_data;
	logic sink_valid, sink_ready, sink_sop, sink_eop;
	logic source_valid, source_ready, source_sop, source_eop;



    initial begin
        $dumpfile("waves.vcd");
        $dumpvars(0, RGB_TO_HSV_TB);

        clk = 0;
		
		repeat (100) begin
            #1 clk = ~clk;
         end

    end
	
	
	
		 
	initial begin
		reset_n = 0;
		
		//Initialization
		sink_data = 24'h0;
		sink_valid = 0;
		sink_sop  = 0;
		sink_eop = 0;
		source_ready = 0;
		
		#2;
		reset_n = 1;
		
		//Packet block
		sink_data = 24'hffffff;
		sink_valid = 0;
		sink_sop  = 0;
		sink_eop = 0;
		source_ready = 1;

		
		
		#4;
		//Packet block
		sink_data = 24'h112233;
		sink_valid = 1;
		sink_sop  = 1;
		sink_eop = 0;
		source_ready = 1;
		
		#2;
		
		//Packet block
		sink_data = 24'h112233;
		sink_valid = 1;
		sink_sop  = 0;
		sink_eop = 0;
		source_ready = 1;
		
		#2;
		//Packet block
		sink_data = 24'h223344;
		sink_valid = 1;
		sink_sop  = 0;
		sink_eop = 0;
		source_ready = 1;
		
		
		
	end
	

RGB_TO_HSV dut(
	.clk(clk),
	.reset_n(reset_n),
	
	
	.sink_data(sink_data),
	.sink_valid(sink_valid),
	.sink_ready(sink_ready),
	.sink_sop(sink_sop),
	.sink_eop(sink_eop),


	.source_data(source_data),
	.source_valid(source_valid),
	.source_ready(source_ready),
	.source_sop(source_sop),
	.source_eop(source_eop)
	); 
endmodule

Broken quartus projects/DE10_CAM_2/ip/RGB_TO_HSV/waves.vcd
$date
	Fri Jun 03 17:04:58 2022
$end
$version
	Icarus Verilog
$end
$timescale
	1s
$end
$scope module RGB_TO_HSV_TB $end
$var wire 1 ! source_valid $end
$var wire 1 " source_sop $end
$var wire 1 # source_eop $end
$var wire 24 $ source_data [23:0] $end
$var wire 1 % sink_ready $end
$var reg 1 & clk $end
$var reg 1 ' reset_n $end
$var reg 24 ( sink_data [23:0] $end
$var reg 1 ) sink_eop $end
$var reg 1 * sink_sop $end
$var reg 1 + sink_valid $end
$var reg 1 , source_ready $end
$scope module dut $end
$var wire 1 & clk $end
$var wire 1 ' reset_n $end
$var wire 24 - sink_data [23:0] $end
$var wire 1 ) sink_eop $end
$var wire 1 * sink_sop $end
$var wire 1 + sink_valid $end
$var wire 1 , source_ready $end
$var wire 1 . valid $end
$var wire 1 ! source_valid $end
$var wire 1 " source_sop $end
$var wire 1 # source_eop $end
$var wire 24 / source_data [23:0] $end
$var wire 1 0 sop $end
$var wire 1 % sink_ready $end
$var wire 24 1 rgb [23:0] $end
$var wire 1 2 ready $end
$var wire 24 3 hsv_comb [23:0] $end
$var wire 1 4 eop $end
$var reg 24 5 hsv [23:0] $end
$scope module in_reg $end
$var wire 1 & clk $end
$var wire 26 6 data_in [25:0] $end
$var wire 1 % ready_out $end
$var wire 1 ' rst_n $end
$var wire 1 + valid_in $end
$var wire 1 . valid_out $end
$var wire 1 2 ready_in $end
$var reg 26 7 data_out [25:0] $end
$var reg 1 8 data_valid $end
$var reg 1 9 ready_in_d $end
$upscope $end
$scope module out_reg $end
$var wire 1 & clk $end
$var wire 26 : data_in [25:0] $end
$var wire 1 , ready_in $end
$var wire 1 2 ready_out $end
$var wire 1 ' rst_n $end
$var wire 1 . valid_in $end
$var wire 1 ! valid_out $end
$var reg 26 ; data_out [25:0] $end
$var reg 1 < data_valid $end
$var reg 1 = ready_in_d $end
$upscope $end
$scope module rgbtohsv $end
$var wire 24 > rgb [23:0] $end
$var reg 9 ? blue [8:0] $end
$var reg 9 @ bmr [8:0] $end
$var reg 8 A cmax [7:0] $end
$var reg 8 B cmin [7:0] $end
$var reg 8 C delta [7:0] $end
$var reg 9 D gmb [8:0] $end
$var reg 9 E green [8:0] $end
$var reg 24 F hsv [23:0] $end
$var reg 8 G hue [7:0] $end
$var reg 17 H hue_step1 [16:0] $end
$var reg 9 I red [8:0] $end
$var reg 9 J rmg [8:0] $end
$var reg 8 K saturation [7:0] $end
$var reg 14 L saturation_intermediate [13:0] $end
$var reg 8 M value [7:0] $end
$scope begin $ivl_for_loop0 $end
$var integer 32 N i [31:0] $end
$upscope $end
$upscope $end
$upscope $end
$upscope $end
$enddefinitions $end
#0
$dumpvars
b100000000 N
bx M
bx L
bx K
bx J
b0xxxxxxxx I
bx H
bx G
bx F
b0xxxxxxxx E
bx D
bx C
bx B
bx A
bx @
b0xxxxxxxx ?
bx >
x=
x<
bx ;
bx :
x9
x8
bx 7
b0 6
bx 5
x4
bx 3
x2
bx 1
x0
bx /
x.
b0 -
0,
0+
0*
0)
b0 (
0'
0&
x%
bx $
x#
x"
x!
$end
#1
12
1%
b0 5
b0 3
b0 F
b0 M
b0 K
b0 L
b0 G
b0 H
b0 C
b0 B
b0 A
b0 J
b0 @
b0 D
b0 ?
b0 E
b0 I
0.
04
b0 :
00
b0 1
b0 >
0!
0#
0"
b0 $
b0 /
09
08
b0 7
0=
0<
b0 ;
1&
#2
0&
1,
b11111111111111111111111100 6
b111111111111111111111111 (
b111111111111111111111111 -
1'
#3
1=
19
1&
#4
0&
#5
1&
#6
0&
1*
1+
b10001001000100011001110 6
b100010010001000110011 (
b100010010001000110011 -
#7
b11010011010100100110011 3
b11010011010100100110011 F
b110011 M
b10101001 K
b10101010000 L
b1101001 G
b1110000000100 H
b100010 C
b10001 B
b110011 A
b111101111 J
b100010 @
b111101111 D
b110011 ?
b100010 E
b10001 I
b100010010001000110011 5
1.
b10001001000100011001110 :
10
b100010010001000110011 1
b100010010001000110011 >
18
b10001001000100011001110 7
1&
#8
0&
b10001001000100011001100 6
0*
#9
b11010011010100100110011 5
b1101001101010010011001100 :
00
1!
1"
b100010010001000110011 $
b100010010001000110011 /
b10001001000100011001100 7
1<
b10001001000100011001110 ;
1&
#10
0&
b100010001100110100010000 6
b1000100011001101000100 (
b1000100011001101000100 -
#11
b1101001011111110100010000 :
b11010010111111101000100 5
b11010010111111101000100 3
b11010010111111101000100 F
b1000100 M
b1111111 K
b1111111100 L
b100010 B
b1000100 A
b1000100 ?
b110011 E
b100010 I
0"
b11010011010100100110011 $
b11010011010100100110011 /
b1000100011001101000100 1
b1000100011001101000100 >
b1101001101010010011001100 ;
b100010001100110100010000 7
1&
#12
0&
#13
b11010010111111101000100 $
b11010010111111101000100 /
b1101001011111110100010000 ;
1&
