EOP_INTERRUPT/STREAM_REG.sv
module STREAM_REG_EOP(ready_out, valid_out, data_out, ready_in, valid_in, data_in, clk, rst_n);

	// Input Port(s)
	input clk, rst_n;
	input ready_in, valid_in;
	input [DATA_WIDTH-1:0] data_in;
	
	// Output Port(s)
	output ready_out, valid_out;
	output reg [DATA_WIDTH-1:0] data_out;

	// Parameter Declaration(s)
	parameter DATA_WIDTH = 26;
	
	reg data_valid, ready_in_d;

	always@(posedge clk) begin
		if (~rst_n) begin
			data_out <= 1'b0;
			data_valid <= 0;
			ready_in_d <= 0;
			end
		else begin
			ready_in_d <= ready_in;
			if (valid_in & (~data_valid | ready_in_d)) begin
				data_out <= data_in;
				data_valid <= 1;
				end
			else if (ready_in_d) begin
				data_valid <= 0;
				end
			end
	end
	
	assign ready_out = (~data_valid & ~valid_in) | ready_in;
	assign valid_out = ready_in_d & data_valid;


endmodule

DE10_CAM_VISION/Qsys/synthesis/submodules/EOP_INTERRUPT.sv
module EOP_INTERRUPT(
	//global clock & reset
	input logic	clk,
	input logic reset_n,
	
	// stream sink
	input logic	[23:0] sink_data,
	input logic sink_valid,
	output logic sink_ready,
	input logic sink_sop,
	input logic sink_eop,
	
	output logic raw_eop,
	output logic raw_sop
	
);

//Intermediate declarations
logic[23:0] data;
logic sop, eop, ready, valid;
logic video_packet;
logic [7:0] irq_d;
logic [7:0] irq_d_sop;


always @(posedge clk) begin
	//Control logic
	if(eop || ~reset_n) begin
		video_packet <= 0;
	end
	else if (sop) begin
		video_packet <= (data[3:0] == 3'h0);
	end
	
	if (video_packet && eop && valid) begin
		irq_d[0] <= 1;
	end else begin
		irq_d[0] <= 0;
	end
	
	if ((data[3:0] == 3'h0) && sop && valid) begin
		irq_d_sop[0] <= 1;
	end else begin
		irq_d_sop[0] <= 0;
	end
	
	//Shift irq
	for (int i = 0; i  < 7; i= i + 1) begin
		irq_d[i+1] <= irq_d[i];
	end
	
	for (int i = 0; i  < 7; i= i + 1) begin
		irq_d_sop[i+1] <= irq_d_sop[i];
	end
end

always @(*) begin	
	if (irq_d > 0) raw_eop = 1;
	else raw_eop = 0;
	
	if (irq_d_sop > 0) raw_sop = 1;
	else raw_sop = 0;
end


//Streaming registers to buffer video signal
STREAM_REG_EOP #(.DATA_WIDTH(26)) in_reg (
	//Global clocks
	.clk(clk),
	.rst_n(reset_n),
	
	//Sink inputs
	.ready_out(sink_ready),
	.valid_in(sink_valid),
	.data_in({sink_data,sink_sop,sink_eop}),
	
	//Internal ports
	.ready_in(1'b1),
	.valid_out(valid),
	.data_out({data,sop,eop})
);

endmodule

DE10_CAM_VISION/ip/EOP_INTERRUPT/EOP_INTERRUPT_TB.sv
module EOP_INTERRUPT_TB ();
	logic [23:0] sink_data, source_data;
	logic clk, reset;
	logic sink_sop, sink_eop, sink_valid, sink_ready, source_sop, source_eop, source_ready, source_valid, irq;
	logic sop, eop;


    initial begin
        $dumpfile("waves.vcd");
        $dumpvars(0, EOP_INTERRUPT_TB);
		
		clk = 0;
		
		repeat (100) begin
            #1 clk = ~clk;
         end
		 
    end
	
	
	
		 
	initial begin
	reset = 0;
	#2;
	reset = 1;
	
	//Avalon packet
	sink_data = 0;
	sink_valid = 0;
	sink_sop = 0;
	sink_eop = 0;
	source_ready = 1;
	
	#2;
	
	//Avalon packet
	sink_data = 0;
	sink_valid = 1;
	sink_sop = 1;
	sink_eop = 0;
	source_ready = 1;
	
	#2;
	
	////Avalon packet
	sink_data = 24'h010203;
	sink_valid = 1;
	sink_sop = 0;
	sink_eop = 0;
	source_ready = 1;
	
	#2;
	
	////Avalon packet
	sink_data = 24'h102030;
	sink_valid = 1;
	sink_sop = 0;
	sink_eop = 1;
	source_ready = 1;
	
	#2;
	////Avalon packet
	sink_data = 0;
	sink_valid = 0;
	sink_sop = 0;
	sink_eop = 0;
	source_ready = 1;
	
	#2;
	
	source_ready = 1;
	
	#20;

	
	
	//Control packet
	
	////Avalon packet
	sink_data = 1;
	sink_valid = 1;
	sink_sop = 1;
	sink_eop = 0;
	source_ready = 1;
	
	#2;
	
	////Avalon packet
	sink_data = 24'h102030;
	sink_valid = 1;
	sink_sop = 0;
	sink_eop = 0;
	source_ready = 1;
	
	#2;
	
	////Avalon packet
	sink_data = 24'h102030;
	sink_valid = 1;
	sink_sop = 0;
	sink_eop = 1;
	source_ready = 1;


	#2;
	
	sink_eop = 0;
	
	
	end
	

EOP_INTERRUPT dut(
	.clk(clk),
	.reset_n(reset),
	
	.sink_data(sink_data),
	.sink_valid(sink_valid),
	.sink_ready(sink_ready),
	.sink_sop(sink_sop),
	.sink_eop(sink_eop),
	
	.raw_eop(eop),
	.raw_sop(sop)
	);

endmodule

DE10_CAM_VISION/ip/EOP_INTERRUPT/waves.vcd
$date
	Sat Jun 18 14:41:56 2022
$end
$version
	Icarus Verilog
$end
$timescale
	1s
$end
$scope module EOP_INTERRUPT_TB $end
$var wire 1 ! sop $end
$var wire 1 " sink_ready $end
$var wire 1 # eop $end
$var reg 1 $ clk $end
$var reg 1 % reset $end
$var reg 24 & sink_data [23:0] $end
$var reg 1 ' sink_eop $end
$var reg 1 ( sink_sop $end
$var reg 1 ) sink_valid $end
$var reg 1 * source_ready $end
$scope module dut $end
$var wire 1 $ clk $end
$var wire 1 % reset_n $end
$var wire 24 + sink_data [23:0] $end
$var wire 1 ' sink_eop $end
$var wire 1 ( sink_sop $end
$var wire 1 ) sink_valid $end
$var wire 1 , valid $end
$var wire 1 - sop $end
$var wire 1 " sink_ready $end
$var wire 1 . eop $end
$var wire 24 / data [23:0] $end
$var reg 8 0 irq_d [7:0] $end
$var reg 8 1 irq_d_sop [7:0] $end
$var reg 1 # raw_eop $end
$var reg 1 ! raw_sop $end
$var reg 1 2 video_packet $end
$scope module in_reg $end
$var wire 1 $ clk $end
$var wire 26 3 data_in [25:0] $end
$var wire 1 4 ready_in $end
$var wire 1 " ready_out $end
$var wire 1 % rst_n $end
$var wire 1 ) valid_in $end
$var wire 1 , valid_out $end
$var reg 26 5 data_out [25:0] $end
$var reg 1 6 data_valid $end
$var reg 1 7 ready_in_d $end
$upscope $end
$scope begin $ivl_for_loop0 $end
$var integer 32 8 i [31:0] $end
$upscope $end
$scope begin $ivl_for_loop1 $end
$var integer 32 9 i [31:0] $end
$upscope $end
$upscope $end
$upscope $end
$enddefinitions $end
#0
$dumpvars
b0 9
b0 8
x7
x6
bx 5
14
bx 3
x2
bx 1
bx 0
bx /
x.
x-
x,
bx +
x*
x)
x(
x'
bx &
0%
0$
x#
1"
x!
$end
#1
0,
0.
0-
b0 /
0!
0#
07
06
b0 5
bx0 1
bx0 0
02
b111 9
b111 8
1$
#2
0$
1*
0'
0(
0)
b0 3
b0 &
b0 +
1%
#3
bx00 1
bx00 0
17
b111 9
b111 8
1$
#4
0$
b10 3
1(
1)
#5
1,
1-
bx000 1
bx000 0
16
b10 5
b111 9
b111 8
1$
#6
0$
0(
b1000000100000001100 3
b10000001000000011 &
b10000001000000011 +
#7
0-
b10000001000000011 /
bx0000 0
b1000000100000001100 5
bx0001 1
12
b111 9
b111 8
1$
#8
0$
1'
b10000001000000011000001 3
b100000010000000110000 &
b100000010000000110000 +
#9
1.
b100000010000000110000 /
bx00000 0
b10000001000000011000001 5
bx00010 1
b111 9
b111 8
1$
#10
0$
0'
0)
b0 3
b0 &
b0 +
#11
0,
bx000100 1
06
bx000001 0
02
b111 9
b111 8
1$
#12
0$
#13
bx0001000 1
bx0000010 0
b111 9
b111 8
1$
#14
0$
#15
1!
1#
b10000 1
b100 0
b111 9
b111 8
1$
#16
0$
#17
b100000 1
b1000 0
b111 9
b111 8
1$
#18
0$
#19
b1000000 1
b10000 0
b111 9
b111 8
1$
#20
0$
#21
b10000000 1
b100000 0
b111 9
b111 8
1$
#22
0$
#23
0!
b0 1
b1000000 0
b111 9
b111 8
1$
#24
0$
#25
b10000000 0
b111 9
b111 8
1$
#26
0$
#27
0#
b0 0
b111 9
b111 8
1$
#28
0$
#29
b111 9
b111 8
1$
#30
0$
#31
b111 9
b111 8
1$
#32
0$
1(
1)
b110 3
b1 &
b1 +
#33
1,
0.
1-
b1 /
16
b110 5
b111 9
b111 8
1$
#34
0$
0(
b10000001000000011000000 3
b100000010000000110000 &
b100000010000000110000 +
#35
0-
b100000010000000110000 /
b10000001000000011000000 5
b111 9
b111 8
1$
#36
0$
b10000001000000011000001 3
1'
#37
1.
b10000001000000011000001 5
b111 9
b111 8
1$
#38
0$
b10000001000000011000000 3
0'
#39
0.
b10000001000000011000000 5
b111 9
b111 8
1$
#40
0$
#41
b111 9
b111 8
1$
#42
0$
#43
b111 9
b111 8
1$
#44
0$
#45
b111 9
b111 8
1$
#46
0$
#47
b111 9
b111 8
1$
#48
0$
#49
b111 9
b111 8
1$
#50
0$
#51
b111 9
b111 8
1$
#52
0$
#53
b111 9
b111 8
1$
#54
0$
#55
b111 9
b111 8
1$
#56
0$
#57
b111 9
b111 8
1$
#58
0$
#59
b111 9
b111 8
1$
#60
0$
#61
b111 9
b111 8
1$
#62
0$
#63
b111 9
b111 8
1$
#64
0$
#65
b111 9
b111 8
1$
#66
0$
#67
b111 9
b111 8
1$
#68
0$
#69
b111 9
b111 8
1$
#70
0$
#71
b111 9
b111 8
1$
#72
0$
#73
b111 9
b111 8
1$
#74
0$
#75
b111 9
b111 8
1$
#76
0$
#77
b111 9
b111 8
1$
#78
0$
#79
b111 9
b111 8
1$
#80
0$
#81
b111 9
b111 8
1$
#82
0$
#83
b111 9
b111 8
1$
#84
0$
#85
b111 9
b111 8
1$
#86
0$
#87
b111 9
b111 8
1$
#88
0$
#89
b111 9
b111 8
1$
#90
0$
#91
b111 9
b111 8
1$
#92
0$
#93
b111 9
b111 8
1$
#94
0$
#95
b111 9
b111 8
1$
#96
0$
#97
b111 9
b111 8
1$
#98
0$
#99
b111 9
b111 8
1$
