EOP_INTERRUPT/STREAM_REG.sv
module STREAM_REG_EOP(ready_out, valid_out, data_out, ready_in, valid_in, data_in, clk, rst_n);

	// Input Port(s)
	input clk, rst_n;
	input ready_in, valid_in;
	input [DATA_WIDTH-1:0] data_in;
	
	// Output Port(s)
	output ready_out, valid_out;
	output reg [DATA_WIDTH-1:0] data_out;

	// Parameter Declaration(s)
	parameter DATA_WIDTH = 26;
	
	reg data_valid, ready_in_d;

	always@(posedge clk) begin
		if (~rst_n) begin
			data_out <= 1'b0;
			data_valid <= 0;
			ready_in_d <= 0;
			end
		else begin
			ready_in_d <= ready_in;
			if (valid_in & (~data_valid | ready_in_d)) begin
				data_out <= data_in;
				data_valid <= 1;
				end
			else if (ready_in_d) begin
				data_valid <= 0;
				end
			end
	end
	
	assign ready_out = (~data_valid & ~valid_in) | ready_in;
	assign valid_out = ready_in_d & data_valid;


endmodule

EOP_INTERRUPT/EOP_INTERRUPT.sv
module EOP_INTERRUPT(
	//global clock & reset
	input logic	clk,
	input logic reset_n,
	
	// stream sink
	input logic	[23:0] sink_data,
	input logic sink_valid,
	output logic sink_ready,
	input logic sink_sop,
	input logic sink_eop,
	
	output logic irq
	
);

//Intermediate declarations
logic[23:0] data;
logic sop, eop, ready, valid;
logic video_packet;


always @(posedge clk) begin
	//Control logic
	if(eop || ~reset_n) begin
		video_packet <= 0;
	end
	else if (sop) begin
		video_packet <= (data[3:0] == 3'h0);
	end
end

always @(*) begin	
	if (video_packet && eop && valid) begin
		irq = 1;
	end else begin
		irq = 0;
	end
end


//Streaming registers to buffer video signal
STREAM_REG_EOP #(.DATA_WIDTH(26)) in_reg (
	//Global clocks
	.clk(clk),
	.rst_n(reset_n),
	
	//Sink inputs
	.ready_out(sink_ready),
	.valid_in(sink_valid),
	.data_in({sink_data,sink_sop,sink_eop}),
	
	//Internal ports
	.ready_in(1'b1),
	.valid_out(valid),
	.data_out({data,sop,eop})
);

endmodule

DE10_CAM_VISION/ip/EOP_INTERRUPT/EOP_INTERRUPT_TB.sv
module EOP_INTERRUPT_TB ();
	logic [23:0] sink_data, source_data;
	logic clk, reset;
	logic sink_sop, sink_eop, sink_valid, sink_ready, source_sop, source_eop, source_ready, source_valid, irq;


    initial begin
        $dumpfile("waves.vcd");
        $dumpvars(0, EOP_INTERRUPT_TB);
		
		clk = 0;
		
		repeat (100) begin
            #1 clk = ~clk;
         end
		 
    end
	
	
	
		 
	initial begin
	reset = 0;
	#2;
	reset = 1;
	
	//Avalon packet
	sink_data = 0;
	sink_valid = 0;
	sink_sop = 0;
	sink_eop = 0;
	source_ready = 1;
	
	#2;
	
	//Avalon packet
	sink_data = 0;
	sink_valid = 1;
	sink_sop = 1;
	sink_eop = 0;
	source_ready = 1;
	
	#2;
	
	////Avalon packet
	sink_data = 24'h010203;
	sink_valid = 1;
	sink_sop = 0;
	sink_eop = 0;
	source_ready = 1;
	
	#2;
	
	////Avalon packet
	sink_data = 24'h102030;
	sink_valid = 1;
	sink_sop = 0;
	sink_eop = 1;
	source_ready = 1;
	
	#2;
	////Avalon packet
	sink_data = 0;
	sink_valid = 0;
	sink_sop = 0;
	sink_eop = 0;
	source_ready = 0;
	
	#2;
	
	source_ready = 0;
	
	#4;
	
	
	//Control packet
	
	////Avalon packet
	sink_data = 1;
	sink_valid = 1;
	sink_sop = 1;
	sink_eop = 0;
	source_ready = 1;
	
	#2;
	
	////Avalon packet
	sink_data = 24'h102030;
	sink_valid = 1;
	sink_sop = 0;
	sink_eop = 0;
	source_ready = 1;
	
	#2;
	
	////Avalon packet
	sink_data = 24'h102030;
	sink_valid = 1;
	sink_sop = 0;
	sink_eop = 1;
	source_ready = 1;


	#2;
	
	sink_eop = 0;
	
	
	end
	

EOP_INTERRUPT dut(
	.clk(clk),
	.reset_n(reset),
	
	.sink_data(sink_data),
	.sink_valid(sink_valid),
	.sink_ready(sink_ready),
	.sink_sop(sink_sop),
	.sink_eop(sink_eop),
	
	.irq(irq)
	);

endmodule

EOP_INTERRUPT/waves.vcd
$date
	Sun Jun 12 10:17:19 2022
$end
$version
	Icarus Verilog
$end
$timescale
	1s
$end
$scope module EOP_INTERRUPT_TB $end
$var wire 1 ! sink_ready $end
$var wire 1 " irq $end
$var reg 1 # clk $end
$var reg 1 $ reset $end
$var reg 24 % sink_data [23:0] $end
$var reg 1 & sink_eop $end
$var reg 1 ' sink_sop $end
$var reg 1 ( sink_valid $end
$var reg 1 ) source_ready $end
$scope module dut $end
$var wire 1 # clk $end
$var wire 1 $ reset_n $end
$var wire 24 * sink_data [23:0] $end
$var wire 1 & sink_eop $end
$var wire 1 ' sink_sop $end
$var wire 1 ( sink_valid $end
$var wire 1 + valid $end
$var wire 1 , sop $end
$var wire 1 ! sink_ready $end
$var wire 1 - eop $end
$var wire 24 . data [23:0] $end
$var reg 1 " irq $end
$var reg 1 / video_packet $end
$scope module in_reg $end
$var wire 1 # clk $end
$var wire 26 0 data_in [25:0] $end
$var wire 1 1 ready_in $end
$var wire 1 ! ready_out $end
$var wire 1 $ rst_n $end
$var wire 1 ( valid_in $end
$var wire 1 + valid_out $end
$var reg 26 2 data_out [25:0] $end
$var reg 1 3 data_valid $end
$var reg 1 4 ready_in_d $end
$upscope $end
$upscope $end
$upscope $end
$enddefinitions $end
#0
$dumpvars
x4
x3
bx 2
11
bx 0
x/
bx .
x-
x,
x+
bx *
x)
x(
x'
x&
bx %
0$
0#
x"
1!
$end
#1
0+
0-
0,
b0 .
0"
04
03
b0 2
0/
1#
#2
0#
1)
0&
0'
0(
b0 0
b0 %
b0 *
1$
#3
14
1#
#4
0#
b10 0
1'
1(
#5
1+
1,
13
b10 2
1#
#6
0#
0'
b1000000100000001100 0
b10000001000000011 %
b10000001000000011 *
#7
0,
b10000001000000011 .
1/
b1000000100000001100 2
1#
#8
0#
1&
b10000001000000011000001 0
b100000010000000110000 %
b100000010000000110000 *
#9
1"
1-
b100000010000000110000 .
b10000001000000011000001 2
1#
#10
0#
0)
0&
0(
b0 0
b0 %
b0 *
#11
0"
0+
0/
03
1#
#12
0#
#13
1#
#14
0#
#15
1#
#16
0#
1)
1'
1(
b110 0
b1 %
b1 *
#17
1+
0-
1,
b1 .
13
b110 2
1#
#18
0#
0'
b10000001000000011000000 0
b100000010000000110000 %
b100000010000000110000 *
#19
0,
b100000010000000110000 .
b10000001000000011000000 2
1#
#20
0#
b10000001000000011000001 0
1&
#21
1-
b10000001000000011000001 2
1#
#22
0#
b10000001000000011000000 0
0&
#23
0-
b10000001000000011000000 2
1#
