DE10_CAM_FRESH/ip/RGB_TO_HSV/RGB_TO_HSV_PIPELINED.sv
module RGB_TO_HSV_PIPELINED(
	input logic advance,
	input logic clk,
	input logic reset,
	input logic	[23:0] rgb,
	output logic [23:0] hsv
);


///////////////////////////////////////////////////////////////////////

//Division lookup table 
logic signed [14:0] div_lookup[255:0];
logic signed[8:0] gmb, bmr, rmg;

logic[7:0] hue, saturation, value, cmin, cmin_comb, cmax, cmax2, cmax_comb, delta, delta_comb;
logic[8:0] red, green, blue;
logic[17:0] hue_step3_1, hue_step3_2;
logic signed[17:0] hue_step2_1, hue_step2_2;
logic signed [8:0] base;
logic signed[3:0] modifier;
logic signed [16:0] hue_debug;
logic base_sign;
logic [7:0] base_magnitude;
logic [14:0] saturation_lookup, saturation_step1, saturation_step2_1, saturation_step2_2;
logic [14:0] hue_lookup;
logic signed[14:0] hue_lookup_original;
logic [14:0] hue_lookup_unsigned;
logic [22:0] saturation_step3;





//Lookup table initialization

initial begin
	div_lookup[0] = 0;
	for (int i = 1; i < 256; i = i+1)  begin
		div_lookup[i] = (1<<12)/i;
	end
end

always @(posedge clk) begin

	if (~reset) begin
		gmb <= 0;
		bmr <= 0;
		rmg <= 0;
		delta <= 0;
		hue_lookup <= 0;
		hue_step2_1 <= 0;
		hue_step2_2 <= 0;
		saturation_lookup <= 0;
		saturation_step2_1 <= 0;
		saturation_step2_2 <= 0;
		cmax <= 0;
		cmax2 <= 0;
	
	end else begin
		//Hue
		//Step 1 ffs
		//Differences
		gmb <= green - blue;
		bmr <= blue - red;
		rmg <= red - green;
		
		//Delta
		delta <= delta_comb;
		hue_lookup <= div_lookup[delta_comb];
		
		
		//Hue step 2 -> Multiplication	
		hue_step2_1 <= base_magnitude * hue_lookup[6:0];
		hue_step2_2 <= base_magnitude * hue_lookup[14:7];
		
		//Saturation
			//Step 1 - > cmax & lookup
		saturation_lookup <= div_lookup[cmax_comb];

		
		
		//Step 2 -> Multiplication
		saturation_step2_1 <= delta * saturation_lookup[6:0];
		saturation_step2_2 <= delta * saturation_lookup[14:7];
		
		
		//Value
		cmax  <= cmax_comb;
		cmax2 <=cmax;
	
	end

end

always @(*) begin
	//Step 1 -> Pre cmax, delta calculation, formatting
	
	//RGB splitting
	red = {1'b0, rgb[23:16]};
	green = {1'b0, rgb[15:8]};
	blue = {1'b0, rgb[7:0]};
	

	
	//Cmax calculation
	if (red >= blue & red >= green) begin 
		cmax_comb = red;
	end else if (green >= red & green >= blue) begin
		cmax_comb = green;
	end else begin
		cmax_comb = blue;
	end
	
	//Cmin calculation
	if (red <= blue & red <= green) cmin_comb = red;
	else if (green <= red & green <= blue) cmin_comb = green;
	else cmin_comb = blue;
	
	delta_comb = cmax_comb-cmin_comb;

	

	//Hue calculation
	if (red >= blue & red >= green) begin 
		if (green >= blue) begin
			base = gmb;
			modifier = 0;
		end else begin
			base = gmb;
			modifier = 6;
		end
			
	end else if (green >= red & green >= blue) begin
		base = bmr;
		modifier = 2;
		
	end else begin
		base = rmg;
		modifier = 4;
	end
	
	base_sign = base[8];
	if (base_sign) base_magnitude = -base;
	else base_magnitude = base;
	

	
	//Step 3 -> Merge
	if (base_sign) begin
		hue_step3_1 = -(hue_step2_1 + (hue_step2_2 << 7));
	end else begin 
		hue_step3_1 = (hue_step2_1 + (hue_step2_2 << 7));
	end
	
	
	hue_step3_2 = hue_step3_1 + (modifier<<<12);
	hue = (30* (hue_step3_2))>>12;


	//Pipelined saturation
	

	//Step 3 -> Merge
	saturation_step3 = saturation_step2_1 + (saturation_step2_2<<7);
	saturation = ((saturation_step3<<8) - saturation_step3) >> 12;
	

	value = cmax2;
		
	hsv = {hue, saturation, value}; 
		
end

endmodule

DE10_CAM_MEMORY/ip/RGB_TO_HSV/STREAM_REG.sv
module STREAM_REG(ready_out, valid_out, data_out, ready_in, valid_in, data_in, clk, rst_n);

	// Input Port(s)
	input clk, rst_n;
	input ready_in, valid_in;
	input [DATA_WIDTH-1:0] data_in;
	
	// Output Port(s)
	output ready_out, valid_out;
	output reg [DATA_WIDTH-1:0] data_out;

	// Parameter Declaration(s)
	parameter DATA_WIDTH = 26;
	
	reg data_valid, ready_in_d;

	always@(posedge clk) begin
		if (~rst_n) begin
			data_out <= 1'b0;
			data_valid <= 0;
			ready_in_d <= 0;
			end
		else begin
			ready_in_d <= ready_in;
			if (valid_in & (~data_valid | ready_in_d)) begin
				data_out <= data_in;
				data_valid <= 1;
				end
			else if (ready_in_d) begin
				data_valid <= 0;
				end
			end
	end
	
	assign ready_out = (~data_valid & ~valid_in) | ready_in;
	assign valid_out = ready_in_d & data_valid;
	//assign advance = valid_in & (~data_valid | ready_in_d);


endmodule

DE10_CAM_MEMORY/ip/RGB_TO_HSV/RGB_TO_HSV_PIPELINED_TOP.sv
module RGB_TO_HSV_PIPELINED_TOP(
	//global clock & reset
	input logic	clk,
	input logic reset_n,
	
	// stream sink
	input logic	[23:0] sink_data,
	input logic sink_valid,
	output logic sink_ready,
	input logic sink_sop,
	input logic sink_eop,
	
	// streaming source
	output logic [23:0] source_data,
	output logic source_valid,
	input logic source_ready,
	output logic source_sop,
	output logic source_eop
	
);

//Intermediate declarations
logic[23:0] rgb, rgb_1, rgb_2, hsv, hsv_comb;
logic sop, eop, ready, valid, selected_hsv;

logic video_packet;
logic valid_1, valid_2;
logic sop_1, sop_2;
logic eop_1, eop_2;
logic advance, ready_d;
logic video_packet_1, video_packet_2, video_packet_3;

always @(posedge clk) begin
	//Control logic
	if(eop || ~reset_n) begin
		video_packet <= 0;
	end
	if (sop) begin
		video_packet <= (rgb[3:0] == 3'h0);
	end
	if (~reset_n)begin
		valid_1 <= 0;
		valid_2 <= 0;
		sop_1 <= 0;
		sop_2 <= 0;
		eop_1 <= 0;
		eop_2 <= 0;
		
	end if (advance) begin
		valid_1 <= valid;
		valid_2 <= valid_1;
		sop_1 <= sop;
		sop_2 <= sop_1;
		eop_1 <= eop;
		eop_2 <= eop_1;
		
		rgb_1 <= rgb;
		rgb_2 <= rgb_1;
		
		video_packet_1 <= video_packet;
		video_packet_2 <= video_packet_1;
		video_packet_3 <= video_packet_2;
	end
	
	ready_d = ready;
end

always @(*) begin
	selected_hsv = video_packet_2 && (~sop_2);
	if (selected_hsv) begin
		hsv = hsv_comb;
	end else begin
		hsv = rgb_2;
	end
	
	advance = ready_d | ~valid_2;
	
end


//Streaming registers to buffer video signal
STREAM_REG #(.DATA_WIDTH(26)) in_reg (
	//Global clocks
	.clk(clk),
	.rst_n(reset_n),
	
	//Sink inputs
	.ready_out(sink_ready),
	.valid_in(sink_valid),
	.data_in({sink_data,sink_sop,sink_eop}),
	
	//Internal ports
	.ready_in(ready),
	.valid_out(valid),
	.data_out({rgb,sop,eop})
);

STREAM_REG #(.DATA_WIDTH(26)) out_reg (
	//Global clocks
	.clk(clk),
	.rst_n(reset_n),
	
	//Internal ports
	.ready_out(ready),
	.valid_in(valid_2),
	.data_in({hsv, sop_2, eop_2}),
	
	//source ports
	
	.ready_in(source_ready),
	.valid_out(source_valid),
	.data_out({source_data,source_sop,source_eop})
);

RGB_TO_HSV_PIPELINED  rgbtohsv (.rgb(rgb), .hsv(hsv_comb), .advance(advance), .clk(clk), .reset(reset_n));

endmodule

DE10_CAM_FILTER/ip/RGB_TO_HSV/RGB_TO_HSV_PIPELINED_TB.sv
module RGB_TO_HSV_COMB_TB ();
	logic [23:0] sink_data, source_data;
	logic clk, reset;
	logic sink_sop, sink_eop, sink_valid, sink_ready, source_sop, source_eop, source_ready, source_valid;


    initial begin
        $dumpfile("waves.vcd");
        $dumpvars(0, RGB_TO_HSV_COMB_TB);
		
		clk = 0;
		
		repeat (100) begin
            #1 clk = ~clk;
         end
		 
    end
	
	
	
		 
	initial begin
	reset = 0;
	#2;
	reset = 1;
	
	//Avalon packet
	sink_data = 0;
	sink_valid = 0;
	sink_sop = 0;
	sink_eop = 0;
	source_ready = 1;
	
	#2;
	
	//Avalon packet
	sink_data = 0;
	sink_valid = 1;
	sink_sop = 1;
	sink_eop = 0;
	source_ready = 1;
	
	#2;
	
	////Avalon packet
	sink_data = 24'h010203;
	sink_valid = 1;
	sink_sop = 0;
	sink_eop = 0;
	source_ready = 1;
	
	#2;
	
	////Avalon packet
	sink_data = 24'h102030;
	sink_valid = 1;
	sink_sop = 0;
	sink_eop = 1;
	source_ready = 1;
	
	#2;
	////Avalon packet
	sink_data = 0;
	sink_valid = 0;
	sink_sop = 0;
	sink_eop = 0;
	source_ready = 0;
	
	#2;
	
	source_ready = 0;
	
	#4;
	
	
	//Control packet
	
	////Avalon packet
	sink_data = 1;
	sink_valid = 1;
	sink_sop = 1;
	sink_eop = 0;
	source_ready = 1;
	
	#2;
	
	////Avalon packet
	sink_data = 24'h102030;
	sink_valid = 1;
	sink_sop = 0;
	sink_eop = 0;
	source_ready = 1;
	
	#2;
	
	////Avalon packet
	sink_data = 24'h102030;
	sink_valid = 1;
	sink_sop = 0;
	sink_eop = 1;
	source_ready = 1;


	#2;
	
	sink_eop = 0;
	
	
	end
	

RGB_TO_HSV_PIPELINED_TOP dut(
	.clk(clk),
	.reset_n(reset),
	.sink_data(sink_data),
	.sink_valid(sink_valid),
	.sink_ready(sink_ready),
	.sink_sop(sink_sop),
	.sink_eop(sink_eop),
	
	
	.source_data(source_data),
	.source_valid(source_valid),
	.source_ready(source_ready),
	.source_sop(source_sop),
	.source_eop(source_eop)
	);

endmodule

DE10_CAM_MEMORY/ip/RGB_TO_HSV/waves.vcd
$date
	Mon Jun 06 17:30:16 2022
$end
$version
	Icarus Verilog
$end
$timescale
	1s
$end
$scope module RGB_TO_HSV_COMB_TB $end
$var wire 1 ! source_valid $end
$var wire 1 " source_sop $end
$var wire 1 # source_eop $end
$var wire 24 $ source_data [23:0] $end
$var wire 1 % sink_ready $end
$var reg 1 & clk $end
$var reg 1 ' reset $end
$var reg 24 ( sink_data [23:0] $end
$var reg 1 ) sink_eop $end
$var reg 1 * sink_sop $end
$var reg 1 + sink_valid $end
$var reg 1 , source_ready $end
$scope module dut $end
$var wire 1 & clk $end
$var wire 1 ' reset_n $end
$var wire 24 - sink_data [23:0] $end
$var wire 1 ) sink_eop $end
$var wire 1 * sink_sop $end
$var wire 1 + sink_valid $end
$var wire 1 , source_ready $end
$var wire 1 . valid $end
$var wire 1 ! source_valid $end
$var wire 1 " source_sop $end
$var wire 1 # source_eop $end
$var wire 24 / source_data [23:0] $end
$var wire 1 0 sop $end
$var wire 1 % sink_ready $end
$var wire 24 1 rgb [23:0] $end
$var wire 1 2 ready $end
$var wire 24 3 hsv_comb [23:0] $end
$var wire 1 4 eop $end
$var reg 1 5 advance $end
$var reg 1 6 eop_1 $end
$var reg 1 7 eop_2 $end
$var reg 24 8 hsv [23:0] $end
$var reg 1 9 ready_d $end
$var reg 24 : rgb_1 [23:0] $end
$var reg 24 ; rgb_2 [23:0] $end
$var reg 1 < selected_hsv $end
$var reg 1 = sop_1 $end
$var reg 1 > sop_2 $end
$var reg 1 ? valid_1 $end
$var reg 1 @ valid_2 $end
$var reg 1 A video_packet $end
$var reg 1 B video_packet_1 $end
$var reg 1 C video_packet_2 $end
$var reg 1 D video_packet_3 $end
$scope module in_reg $end
$var wire 1 & clk $end
$var wire 26 E data_in [25:0] $end
$var wire 1 % ready_out $end
$var wire 1 ' rst_n $end
$var wire 1 + valid_in $end
$var wire 1 . valid_out $end
$var wire 1 2 ready_in $end
$var reg 26 F data_out [25:0] $end
$var reg 1 G data_valid $end
$var reg 1 H ready_in_d $end
$upscope $end
$scope module out_reg $end
$var wire 1 & clk $end
$var wire 26 I data_in [25:0] $end
$var wire 1 , ready_in $end
$var wire 1 2 ready_out $end
$var wire 1 ' rst_n $end
$var wire 1 @ valid_in $end
$var wire 1 ! valid_out $end
$var reg 26 J data_out [25:0] $end
$var reg 1 K data_valid $end
$var reg 1 L ready_in_d $end
$upscope $end
$scope module rgbtohsv $end
$var wire 1 5 advance $end
$var wire 1 & clk $end
$var wire 1 ' reset $end
$var wire 24 M rgb [23:0] $end
$var reg 9 N base [8:0] $end
$var reg 8 O base_magnitude [7:0] $end
$var reg 1 P base_sign $end
$var reg 9 Q blue [8:0] $end
$var reg 9 R bmr [8:0] $end
$var reg 8 S cmax [7:0] $end
$var reg 8 T cmax2 [7:0] $end
$var reg 8 U cmax_comb [7:0] $end
$var reg 8 V cmin_comb [7:0] $end
$var reg 8 W delta [7:0] $end
$var reg 8 X delta_comb [7:0] $end
$var reg 9 Y gmb [8:0] $end
$var reg 9 Z green [8:0] $end
$var reg 24 [ hsv [23:0] $end
$var reg 8 \ hue [7:0] $end
$var reg 15 ] hue_lookup [14:0] $end
$var reg 18 ^ hue_step2_1 [17:0] $end
$var reg 18 _ hue_step2_2 [17:0] $end
$var reg 18 ` hue_step3_1 [17:0] $end
$var reg 18 a hue_step3_2 [17:0] $end
$var reg 4 b modifier [3:0] $end
$var reg 9 c red [8:0] $end
$var reg 9 d rmg [8:0] $end
$var reg 8 e saturation [7:0] $end
$var reg 15 f saturation_lookup [14:0] $end
$var reg 15 g saturation_step2_1 [14:0] $end
$var reg 15 h saturation_step2_2 [14:0] $end
$var reg 23 i saturation_step3 [22:0] $end
$var reg 8 j value [7:0] $end
$scope begin $ivl_for_loop0 $end
$var integer 32 k i [31:0] $end
$upscope $end
$upscope $end
$upscope $end
$upscope $end
$enddefinitions $end
#0
$dumpvars
b100000000 k
bx j
bx i
bx h
bx g
bx f
bx e
bx d
bx c
bx b
bx a
bx `
bx _
bx ^
bx ]
bx \
bx [
bx Z
bx Y
bx X
bx W
bx V
bx U
bx T
bx S
bx R
bx Q
xP
bx O
bx N
bx M
xL
xK
bx J
bx I
xH
xG
bx F
bx E
xD
xC
xB
xA
x@
x?
x>
x=
x<
bx ;
bx :
x9
bx 8
x7
x6
x5
x4
bx 3
x2
bx 1
x0
bx /
x.
bx -
x,
x+
x*
x)
bx (
0'
0&
x%
bx $
x#
x"
x!
$end
#1
1%
12
b0 X
b0 V
b0 U
0.
04
00
b0 1
b0 M
0!
0#
0"
b0 $
b0 /
b0 3
b0 [
b0 j
b0 e
b0 i
b0 \
b0 a
b0 `
b0 O
0P
b0 b
b0 N
b0 Q
b0 Z
b0 c
15
0H
0G
b0 F
0L
0K
b0 J
b0 T
b0 S
b0 h
b0 g
b0 f
b0 _
b0 ^
b0 ]
b0 W
b0 d
b0 R
b0 Y
07
06
bx00 I
0>
0=
0@
0?
0A
1&
#2
0&
1,
0)
0*
0+
b0 E
b0 (
b0 -
1'
#3
0B
b0 :
1L
1H
19
1&
#4
0&
b10 E
1*
1+
#5
1.
10
b0 I
b0 8
0<
1G
b10 F
0C
b0 ;
1&
#6
0&
0*
b1000000100000001100 E
b10000001000000011 (
b10000001000000011 -
#7
b11110000000000000000000 3
b11110000000000000000000 [
b1111000 \
b100000000000000 a
b100 b
b10 X
b1 V
b11 U
b11 Q
b10 Z
b1 c
00
b10000001000000011 1
b10000001000000011 M
0D
1=
1?
1A
b1000000100000001100 F
1&
#8
0&
1)
b10000001000000011000001 E
b100000010000000110000 (
b100000010000000110000 -
#9
b100000 X
b10000 V
b110000 U
b110000 Q
b100000 Z
b10000 c
14
b100000010000000110000 1
b100000010000000110000 M
b1 O
1P
b111111111 N
b10000001000000011000001 F
b11 S
b10101010101 f
b100000000000 ]
b10 W
b111111111 d
b10 R
b111111111 Y
1B
b10000001000000011 :
b10 I
1>
0=
1@
1&
#10
0%
02
0&
0,
0)
0+
b0 E
b0 (
b0 -
#11
1%
b11010011010100100000011 8
1<
b11010011010100100000011 3
b11010011010100100000011 [
b11 j
b10101001 e
b101010101010 i
b1101001 \
b11100000000000 a
b111111100000000000 `
b10000 O
b111110000 N
1"
0.
1C
b10000001000000011 ;
b100000010000000110000 :
16
b1101001101010010000001100 I
0>
0A
b11 T
b110000 S
b10100 h
b10101010 g
b1010101 f
b10000 _
b10000000 ]
b100000 W
b111110000 d
b100000 R
b111110000 Y
1K
b10 J
0L
0G
0H
05
09
1&
#12
0&
#13
b1101001101010010011000000 I
b11010011010100100110000 8
b11010011010100100110000 3
b11010011010100100110000 [
b110000 j
b101010100000 i
b110000 T
b0 h
b101010100000 g
1&
#14
0&
#15
1&
#16
12
0&
1,
1*
1+
b110 E
b1 (
b1 -
#17
b1 X
b0 V
b1 U
b1 Q
b0 Z
b0 c
04
10
b1 1
b1 M
1.
1!
1G
b110 F
1H
1L
15
19
1&
#18
0&
0*
b10000001000000011000000 E
b100000010000000110000 (
b100000010000000110000 -
#19
b100001111010100100110000 8
b100001111010100100110000 3
b100001111010100100110000 [
b10000111 \
b100100000000000 a
b100000000000 `
b0 O
0P
b0 N
b100000 X
b10000 V
b110000 U
b110000 Q
b100000 Z
b10000 c
0"
b11010011010100100110000 $
b11010011010100100110000 /
00
b100000010000000110000 1
b100000010000000110000 M
1D
0B
b100000010000000110000 ;
b1 :
b10000111101010010011000001 I
17
06
1=
b1 S
b1000000000000 f
b1000000000000 ]
b1 W
b0 d
b1 R
b111111111 Y
b1101001101010010011000000 J
b10000001000000011000000 F
1&
#20
0&
b10000001000000011000001 E
1)
#21
14
1#
b100001111010100100110000 $
b100001111010100100110000 /
b11110001111111100000001 3
b11110001111111100000001 [
b1 j
b11111111 e
b1000000000000 i
b1111000 \
b100000000000000 a
b0 `
b10000 O
1P
b111110000 N
b1 8
0<
b10000001000000011000001 F
b10000111101010010011000001 J
b1 T
b110000 S
b100000 h
b0 g
b1010101 f
b0 _
b10000000 ]
b100000 W
b111110000 d
b100000 R
b111110000 Y
0C
b1 ;
b100000010000000110000 :
07
b110 I
1>
0=
1&
#22
0&
b10000001000000011000000 E
0)
#23
b100000010000000110000 8
b11010011010100100110000 3
b11010011010100100110000 [
b110000 j
b10101001 e
b101010100000 i
b1101001 \
b11100000000000 a
b111111100000000000 `
0#
1"
b1 $
b1 /
04
0D
b100000010000000110000 ;
16
b10000001000000011000000 I
0>
b110000 T
b0 h
b101010100000 g
b10000 _
b110 J
b10000001000000011000000 F
1&
#24
0&
#25
0"
b100000010000000110000 $
b100000010000000110000 /
b10000001000000011000000 J
b10000001000000011000001 I
17
06
1&
#26
0&
#27
1#
b10000001000000011000000 I
07
b10000001000000011000001 J
1&
#28
0&
#29
0#
b10000001000000011000000 J
1&
